MANIFEST.in
README.md
setup.cfg
setup.py
activewatch/__init__.py
activewatch/asset_model_schema.py
activewatch/client.py
activewatch/config.py
activewatch/constants.py
activewatch/deployments.py
activewatch/region.py
activewatch/service.py
activewatch/session.py
activewatch.egg-info/PKG-INFO
activewatch.egg-info/SOURCES.txt
activewatch.egg-info/dependency_links.txt
activewatch.egg-info/not-zip-safe
activewatch.egg-info/requires.txt
activewatch.egg-info/top_level.txt
activewatch/apis/assets_query.v1.yaml
activewatch/apis/deployment_manager.v1.yaml
activewatch/apis/themis.v1.yaml
activewatch/services/__init__.py
activewatch/services/aims.py
activewatch/services/assets_write.py
activewatch/services/credentials.py
activewatch/services/deployments.py
activewatch/services/scan_result.py