Metadata-Version: 2.1
Name: activewatch
Version: 1.0.5
Summary: The Alert Logic ActiveWatch SDK for Python.
Home-page: https://github.com/alertlogic/activewatch
Author: Alert Logic Inc.
Author-email: support@alertlogic.com
License: MIT
Keywords: activewatch,alertlogic
Platform: any
Requires-Python: >=3.7
Provides-Extra: dev
